.gitignore
LICENSE
README.md
setup.py
examples/cartpole.py
neatest/MPI.py
neatest/__init__.py
neatest/__init__.pyi
neatest/connection.py
neatest/genome.py
neatest/neatest.py
neatest/node.py
neatest/optimizers.py
neatest/plot.py
neatest/py.typed
neatest/version.py
nesneat.egg-info/PKG-INFO
nesneat.egg-info/SOURCES.txt
nesneat.egg-info/dependency_links.txt
nesneat.egg-info/requires.txt
nesneat.egg-info/top_level.txt
tests/__init__.py
tests/test_connection.py
tests/test_genome.py
tests/test_node.py
videos/DoubleInvertedPendulum.gif
videos/LunarLander.gif
videos/LunarLander2.gif