Metadata-Version: 2.1
Name: nesneat
Version: 1.0.7
Summary: Evolving Neural Networks through Augmenting Topologies withEvolution Strategy Training
Home-page: UNKNOWN
Author: Göktuğ Karakaşlı
Author-email: karakasligk@gmail.com
License: MIT
Platform: UNKNOWN
Classifier: Programming Language :: Python :: 3
Classifier: License :: OSI Approved :: MIT License
Requires-Python: >=3.6
License-File: LICENSE
